dsi_cookbook/__init__.py
dsi_cookbook/__main__.py
dsi_cookbook/commands/ingredient.py
dsi_cookbook/commands/recipe.py
dsi_cookbook/main.py
dsi_cookbook-0.1.1.dist-info/entry_points.txt
dsi_cookbook-0.1.1.dist-info/WHEEL
dsi_cookbook-0.1.1.dist-info/METADATA
dsi_cookbook-0.1.1.dist-info/RECORD
