Metadata-Version: 2.1
Name: dsi-cookbook
Version: 0.1.1
Summary: The only cookbook you'll ever need
Author: Qiushi Yan
Author-email: qiushi.yann@gmail.com
Requires-Python: >=3.6,<4.0
Classifier: Programming Language :: Python :: 3
Classifier: Programming Language :: Python :: 3.10
Classifier: Programming Language :: Python :: 3.6
Classifier: Programming Language :: Python :: 3.7
Classifier: Programming Language :: Python :: 3.8
Classifier: Programming Language :: Python :: 3.9
Requires-Dist: typer (>=0.3.0,<0.4.0)
Requires-Dist: typer-cli (>=0.0.12,<0.0.13)
